tmnt/__init__.py
tmnt/configuration.py
tmnt/data_loading.py
tmnt/distribution.py
tmnt/estimator.py
tmnt/eval_npmi.py
tmnt/inference.py
tmnt/modeling.py
tmnt/preprocess/__init__.py
tmnt/preprocess/tokenizer.py
tmnt/preprocess/vectorizer.py
tmnt/sparse/__init__.py
tmnt/sparse/config.py
tmnt/sparse/estimator.py
tmnt/sparse/inference.py
tmnt/sparse/modeling.py
tmnt/utils/__init__.py
tmnt/utils/csv2json.py
tmnt/utils/log_utils.py
tmnt/utils/mat_utils.py
tmnt/utils/ngram_helpers.py
tmnt/utils/pubmed_utils.py
tmnt/utils/random.py
tmnt/utils/recalibrate.py
tmnt/utils/vocab.py
tmnt-0.7.62.dist-info/licenses/LICENSE
tmnt-0.7.62.dist-info/licenses/NOTICE
tmnt-0.7.62.dist-info/METADATA
tmnt-0.7.62.dist-info/WHEEL
tmnt-0.7.62.dist-info/top_level.txt
tmnt-0.7.62.dist-info/RECORD
